model_resolver/__init__.py
model_resolver/item_model/__init__.py
model_resolver/item_model/data_component_predicate.py
model_resolver/item_model/item.py
model_resolver/item_model/model.py
model_resolver/item_model/special.py
model_resolver/item_model/tint_source.py
model_resolver/minecraft_model.py
model_resolver/missingno.png
model_resolver/my_glut_init.py
model_resolver/plugins.py
model_resolver/py.typed
model_resolver/render.py
model_resolver/static_models/assets/minecraft/blockstates/chest.json
model_resolver/static_models/assets/minecraft/blockstates/trapped_chest.json
model_resolver/static_models/assets/minecraft/models/block/chest.json
model_resolver/static_models/assets/minecraft/models/block/chest_left.json
model_resolver/static_models/assets/minecraft/models/block/chest_right.json
model_resolver/static_models/assets/minecraft/models/block/ender_chest.json
model_resolver/static_models/assets/minecraft/models/block/generic_chest.json
model_resolver/static_models/assets/minecraft/models/block/generic_chest_left.json
model_resolver/static_models/assets/minecraft/models/block/generic_chest_right.json
model_resolver/static_models/assets/minecraft/models/block/player_head.json
model_resolver/static_models/assets/minecraft/models/block/trapped_chest.json
model_resolver/static_models/assets/minecraft/models/block/trapped_chest_left.json
model_resolver/static_models/assets/minecraft/models/block/trapped_chest_right.json
model_resolver/tasks/base.py
model_resolver/tasks/generic_render.py
model_resolver/tasks/item.py
model_resolver/tasks/model.py
model_resolver/tasks/structure.py
model_resolver/utils.py
model_resolver-1.13.0.dist-info/LICENSE
model_resolver-1.13.0.dist-info/METADATA
model_resolver-1.13.0.dist-info/WHEEL
model_resolver-1.13.0.dist-info/entry_points.txt
model_resolver-1.13.0.dist-info/RECORD
