Metadata-Version: 2.1
Name: model-resolver
Version: 1.13.0
Summary: 
License: MIT
Author: edayot
Author-email: pro.e.dayot@gmail.com
Requires-Python: >=3.14,<4.0
Classifier: License :: OSI Approved :: MIT License
Classifier: Programming Language :: Python :: 3
Requires-Dist: beet (>=0.113.0-beta.10)
Requires-Dist: click (>=8.1.7)
Requires-Dist: pillow (>10.3.0)
Requires-Dist: pyopengl (>=3.1.9,<4.0.0)
Requires-Dist: rich (>=13.7.1)
Requires-Dist: tqdm (>=4.66.2)
